setup.py
My_Serializer_For_Json_And_XML_For_Lab3_7.egg-info/PKG-INFO
My_Serializer_For_Json_And_XML_For_Lab3_7.egg-info/SOURCES.txt
My_Serializer_For_Json_And_XML_For_Lab3_7.egg-info/dependency_links.txt
My_Serializer_For_Json_And_XML_For_Lab3_7.egg-info/top_level.txt
Serializators/Factory.py
Serializators/JSON.py
Serializators/Meta.py
Serializators/Shell.py
Serializators/XML.py
Serializators/__init__.py
Serializators/constants.py
Serializators/functions_for_deserialize.py
Serializators/functions_for_serializer.py